[
    {
        "event": "New writer in town",
        "agencies": {
            "agency A": {
                "titles": [
                    {
                        "text": "Rats are Taking Over!!!!",
                        "discourse": 10,
                        "money": 100
                    },
                    {
                        "text": "Rats the Facts",
                        "discourse": 1984,
                        "money": 10
                    }
                ],
                "content": [
                    {
                        "text": "The rats killed someone at 9am...",
                        "discourse": 1000,
                        "money": 1000000
                    }
                ],
                "images": [
                    {
                        "text": "res://Art/RatsKillingPerson.jpg",
                        "discourse": 100,
                        "money": 10000
                    }
                ],
                "captions": [
                    {
                        "text": "hello",
                        "discourse": 1,
                        "money": 1
                    }
                ],
                "interviews": [
                    {
                        "text": "I am a art expert and I am scared",
                        "discourse": 100,
                        "money": 234834095834
                    }
                ],
                "studies": [
                    {
                        "text": "Arts are bad mostly but sometimes ok",
                        "discourse": 23904,
                        "money": 092384203948
                    }
                ]
            },
            "agency B": {
                "titles": [],
                "content": [],
                "images": [],
                "captions": [],
                "interviews": [],
                "studies": []
            },
            "agency C": {
                "titles": [],
                "content": [],
                "images": [],
                "captions": [],
                "interviews": [],
                "studies": []
            }
        }
    },
    {
        "event": "Rat Infestation",
        "agencies": {
            "agency A": {
                "titles": [],
                "content": [],
                "images": [],
                "captions": [],
                "interviews": [],
                "studies": []
            },
            "agency B": {
                "titles": [],
                "content": [],
                "images": [],
                "captions": [],
                "interviews": [],
                "studies": []
            },
            "agency C": {
                "titles": [],
                "content": [],
                "images": [],
                "captions": [],
                "interviews": [],
                "studies": []
            }
            
        }
    },
    {
        "event": "City in Unrest",
        "agencies": {
            "agency A": {
                "titles": [],
                "content": [],
                "images": [],
                "captions": [],
                "interviews": [],
                "studies": []
            },
            "agency B": {
                "titles": [],
                "content": [],
                "images": [],
                "captions": [],
                "interviews": [],
                "studies": []
            },
            "agency C": {
                "titles": [],
                "content": [],
                "images": [],
                "captions": [],
                "interviews": [],
                "studies": []
            }
            
        }
    },
    {
        "event": "Rat Infestation Decreased",
        "agencies": {
            "agency A": {
                "titles": [],
                "content": [],
                "images": [],
                "captions": [],
                "interviews": [],
                "studies": []
            },
            "agency B": {
                "titles": [],
                "content": [],
                "images": [],
                "captions": [],
                "interviews": [],
                "studies": []
            },
            "agency C": {
                "titles": [],
                "content": [],
                "images": [],
                "captions": [],
                "interviews": [],
                "studies": []
            }
            
        }
    },
    {
        "event": "Rat Riots",
        "agencies": {
            "agency A": {
                "titles": [],
                "content": [],
                "images": [],
                "captions": [],
                "interviews": [],
                "studies": []
            },
            "agency B": {
                "titles": [],
                "content": [],
                "images": [],
                "captions": [],
                "interviews": [],
                "studies": []
            },
            "agency C": {
                "titles": [],
                "content": [],
                "images": [],
                "captions": [],
                "interviews": [],
                "studies": []
            }
            
        }
    },
    {
        "event": "Mayor makes speach reguarding Rat issue",
        "agencies": {
            "agency A": {
                "titles": [],
                "content": [],
                "images": [],
                "captions": [],
                "interviews": [],
                "studies": []
            },
            "agency B": {
                "titles": [],
                "content": [],
                "images": [],
                "captions": [],
                "interviews": [],
                "studies": []
            },
            "agency C": {
                "titles": [],
                "content": [],
                "images": [],
                "captions": [],
                "interviews": [],
                "studies": []
            }
            
        }
    },
    {
        "event": "City of peace",
        "agencies": {
            "agency A": {
                "titles": [],
                "content": [],
                "images": [],
                "captions": [],
                "interviews": [],
                "studies": []
            },
            "agency B": {
                "titles": [],
                "content": [],
                "images": [],
                "interviews": [],
                "studies": []
            },
            "agency C": {
                "titles": [],
                "content": [],
                "images": [],
                "captions": [],
                "interviews": [],
                "studies": []
            }
            
        }
    }
]